weba/__init__.py
weba/component.py
weba/component_tag.py
weba/context.py
weba/errors.py
weba/tag.py
weba/tag.pyi
weba/tag_decorator.py
weba/ui.py
weba-0.2.32.dist-info/licenses/LICENSE
weba-0.2.32.dist-info/METADATA
weba-0.2.32.dist-info/WHEEL
weba-0.2.32.dist-info/top_level.txt
weba-0.2.32.dist-info/RECORD
