Metadata-Version: 2.4
Name: weba
Version: 0.2.32
Summary: html framework
Author-email: CJ Lazell <cjlazell@gmail.com>
Project-URL: Homepage, https://cj.github.io/weba/
Project-URL: Repository, https://github.com/cj/weba
Project-URL: Documentation, https://cj.github.io/weba/
Keywords: weba,htmx,python
Classifier: Intended Audience :: Developers
Classifier: Programming Language :: Python
Classifier: Programming Language :: Python :: 3
Classifier: Programming Language :: Python :: 3.10
Classifier: Programming Language :: Python :: 3.11
Classifier: Programming Language :: Python :: 3.12
Classifier: Programming Language :: Python :: 3.13
Classifier: Topic :: Software Development :: Libraries :: Python Modules
Requires-Python: <=3.13,>=3.11
License-File: LICENSE
Requires-Dist: beautifulsoup4>=4
Requires-Dist: charset-normalizer>=3.4.0
Requires-Dist: types-beautifulsoup4>=4
Dynamic: license-file
